CHANGELOG.rst
MANIFEST.in
README.md
setup.py
ckeditorfiles/__init__.py
ckeditorfiles/models.py
ckeditorfiles/widgets.py
ckeditorfiles/static/ckeditorfiles/CHANGES.md
ckeditorfiles/static/ckeditorfiles/LICENSE.md
ckeditorfiles/static/ckeditorfiles/README.md
ckeditorfiles/static/ckeditorfiles/build-config.js
ckeditorfiles/static/ckeditorfiles/ckeditor.js
ckeditorfiles/static/ckeditorfiles/config.js
ckeditorfiles/static/ckeditorfiles/contents.css
ckeditorfiles/static/ckeditorfiles/styles.js
ckeditorfiles/static/ckeditorfiles/lang/af.js
ckeditorfiles/static/ckeditorfiles/lang/ar.js
ckeditorfiles/static/ckeditorfiles/lang/bg.js
ckeditorfiles/static/ckeditorfiles/lang/bn.js
ckeditorfiles/static/ckeditorfiles/lang/bs.js
ckeditorfiles/static/ckeditorfiles/lang/ca.js
ckeditorfiles/static/ckeditorfiles/lang/cs.js
ckeditorfiles/static/ckeditorfiles/lang/cy.js
ckeditorfiles/static/ckeditorfiles/lang/da.js
ckeditorfiles/static/ckeditorfiles/lang/de.js
ckeditorfiles/static/ckeditorfiles/lang/el.js
ckeditorfiles/static/ckeditorfiles/lang/en-au.js
ckeditorfiles/static/ckeditorfiles/lang/en-ca.js
ckeditorfiles/static/ckeditorfiles/lang/en-gb.js
ckeditorfiles/static/ckeditorfiles/lang/en.js
ckeditorfiles/static/ckeditorfiles/lang/eo.js
ckeditorfiles/static/ckeditorfiles/lang/es.js
ckeditorfiles/static/ckeditorfiles/lang/et.js
ckeditorfiles/static/ckeditorfiles/lang/eu.js
ckeditorfiles/static/ckeditorfiles/lang/fa.js
ckeditorfiles/static/ckeditorfiles/lang/fi.js
ckeditorfiles/static/ckeditorfiles/lang/fo.js
ckeditorfiles/static/ckeditorfiles/lang/fr-ca.js
ckeditorfiles/static/ckeditorfiles/lang/fr.js
ckeditorfiles/static/ckeditorfiles/lang/gl.js
ckeditorfiles/static/ckeditorfiles/lang/gu.js
ckeditorfiles/static/ckeditorfiles/lang/he.js
ckeditorfiles/static/ckeditorfiles/lang/hi.js
ckeditorfiles/static/ckeditorfiles/lang/hr.js
ckeditorfiles/static/ckeditorfiles/lang/hu.js
ckeditorfiles/static/ckeditorfiles/lang/is.js
ckeditorfiles/static/ckeditorfiles/lang/it.js
django_ckeditor_improved.egg-info/PKG-INFO
django_ckeditor_improved.egg-info/SOURCES.txt
django_ckeditor_improved.egg-info/dependency_links.txt
django_ckeditor_improved.egg-info/not-zip-safe
django_ckeditor_improved.egg-info/top_level.txt