Metadata-Version: 1.1
Name: django-ckeditor-improved
Version: 1.8
Summary: CKEditor bundled as a django staticfiles app.
Home-page: https://github.com/ninapavlich/django_ckeditor_improved
Author: Nina Pavlich
Author-email: nina@ninalp.com
License: BSD
Platform: UNKNOWN
Classifier: Development Status :: 5 - Production/Stable
Classifier: Environment :: Web Environment
Classifier: Framework :: Django
Classifier: Intended Audience :: Developers
Classifier: License :: OSI Approved
Classifier: Operating System :: OS Independent
Classifier: Programming Language :: Python
